{"created_at":"Tue Oct 23 01:55:51 +0000 2018","id":1054551945917222913,"id_str":"1054551945917222913","text":"@92jinlovrs Alguien expliqueme \n\u00bfEn que capitulo vas de Hello My Twenties?","display_text_range":[12,74],"source":"\u003ca href=\"http:\/\/twitter.com\/download\/android\" rel=\"nofollow\"\u003eTwitter for Android\u003c\/a\u003e","truncated":false,"in_reply_to_status_id":1054549458132889601,"in_reply_to_status_id_str":"1054549458132889601","in_reply_to_user_id":941027962144555008,"in_reply_to_user_id_str":"941027962144555008","in_reply_to_screen_name":"92jinlovrs","user":{"id":955666282925494272,"id_str":"955666282925494272","name":"Vale  #Monoiscoming #RM2","screen_name":"RMJHVJKJNSGJM","location":"Nueva Republica ARMY","url":null,"description":"ARMY 10000%\nBANGTAN BIASED\nM U L T I F A N D O M","translator_type":"none","protected":false,"verified":false,"followers_count":93,"friends_count":335,"listed_count":0,"favourites_count":3044,"statuses_count":2510,"created_at":"Tue Jan 23 04:59:32 +0000 2018","utc_offset":null,"time_zone":null,"geo_enabled":false,"lang":"es","contributors_enabled":false,"is_translator":false,"profile_background_color":"F5F8FA","profile_background_image_url":"","profile_background_image_url_https":"","profile_background_tile":false,"profile_link_color":"1DA1F2","profile_sidebar_border_color":"C0DEED","profile_sidebar_fill_color":"DDEEF6","profile_text_color":"333333","profile_use_background_image":true,"profile_image_url":"http:\/\/pbs.twimg.com\/profile_images\/1049792437588303872\/dXB9RSeg_normal.jpg","profile_image_url_https":"https:\/\/pbs.twimg.com\/profile_images\/1049792437588303872\/dXB9RSeg_normal.jpg","profile_banner_url":"https:\/\/pbs.twimg.com\/profile_banners\/955666282925494272\/1540057834","default_profile":true,"default_profile_image":false,"following":null,"follow_request_sent":null,"notifications":null},"geo":null,"coordinates":null,"place":null,"contributors":null,"is_quote_status":false,"quote_count":0,"reply_count":0,"retweet_count":0,"favorite_count":0,"entities":{"hashtags":[],"urls":[],"user_mentions":[{"screen_name":"92jinlovrs","name":"\u1d04\u029c\u1d0f\u0280\u026a\u0299\u1d00\u0274\u0262 \ud83c\udde6\ud83c\uddf7 \u043cono","id":941027962144555008,"id_str":"941027962144555008","indices":[0,11]}],"symbols":[]},"favorited":false,"retweeted":false,"filter_level":"low","lang":"es","timestamp_ms":"1540259751191"}
{"created_at":"Tue Oct 23 01:55:51 +0000 2018","id":1054551946537906176,"id_str":"1054551946537906176","text":"RT @SuelyLima17: @samalvesmusic E a\u00ed que achei muito criativo dizer : Sim com Hello  \ud83d\ude0de n\u00e3o com ByeBye! \ud83d\ude22 Demais!!! amei!","source":"\u003ca href=\"http:\/\/twitter.com\/download\/android\" rel=\"nofollow\"\u003eTwitter for Android\u003c\/a\u003e","truncated":false,"in_reply_to_status_id":null,"in_reply_to_status_id_str":null,"in_reply_to_user_id":null,"in_reply_to_user_id_str":null,"in_reply_to_screen_name":null,"user":{"id":971867405738823681,"id_str":"971867405738823681","name":"William Sousa","screen_name":"William22762746","location":"Teresina, Brasil","url":null,"description":null,"translator_type":"none","protected":false,"verified":false,"followers_count":40,"friends_count":234,"listed_count":0,"favourites_count":12902,"statuses_count":10846,"created_at":"Thu Mar 08 21:57:00 +0000 2018","utc_offset":null,"time_zone":null,"geo_enabled":false,"lang":"en","contributors_enabled":false,"is_translator":false,"profile_background_color":"F5F8FA","profile_background_image_url":"","profile_background_image_url_https":"","profile_background_tile":false,"profile_link_color":"1DA1F2","profile_sidebar_border_color":"C0DEED","profile_sidebar_fill_color":"DDEEF6","profile_text_color":"333333","profile_use_background_image":true,"profile_image_url":"http:\/\/pbs.twimg.com\/profile_images\/998743174980845568\/CqWD7BsA_normal.jpg","profile_image_url_https":"https:\/\/pbs.twimg.com\/profile_images\/998743174980845568\/CqWD7BsA_normal.jpg","default_profile":true,"default_profile_image":false,"following":null,"follow_request_sent":null,"notifications":null},"geo":null,"coordinates":null,"place":null,"contributors":null,"retweeted_status":{"created_at":"Sun Oct 21 22:46:47 +0000 2018","id":1054141977728561152,"id_str":"1054141977728561152","text":"@samalvesmusic E a\u00ed que achei muito criativo dizer : Sim com Hello  \ud83d\ude0de n\u00e3o com ByeBye! \ud83d\ude22 Demais!!! amei!","display_text_range":[15,104],"source":"\u003ca href=\"http:\/\/twitter.com\" rel=\"nofollow\"\u003eTwitter Web Client\u003c\/a\u003e","truncated":false,"in_reply_to_status_id":1053769302590001153,"in_reply_to_status_id_str":"1053769302590001153","in_reply_to_user_id":855216613,"in_reply_to_user_id_str":"855216613","in_reply_to_screen_name":"samalvesmusic","user":{"id":2275915428,"id_str":"2275915428","name":"Suely Lima","screen_name":"SuelyLima17","location":null,"url":null,"description":null,"translator_type":"none","protected":false,"verified":false,"followers_count":309,"friends_count":64,"listed_count":0,"favourites_count":4840,"statuses_count":35995,"created_at":"Sat Jan 04 10:25:33 +0000 2014","utc_offset":null,"time_zone":null,"geo_enabled":false,"lang":"pt","contributors_enabled":false,"is_translator":false,"profile_background_color":"000000","profile_background_image_url":"http:\/\/abs.twimg.com\/images\/themes\/theme1\/bg.png","profile_background_image_url_https":"https:\/\/abs.twimg.com\/images\/themes\/theme1\/bg.png","profile_background_tile":false,"profile_link_color":"3B94D9","profile_sidebar_border_color":"000000","profile_sidebar_fill_color":"000000","profile_text_color":"000000","profile_use_background_image":false,"profile_image_url":"http:\/\/pbs.twimg.com\/profile_images\/1037099983252738055\/9t5FFbFx_normal.jpg","profile_image_url_https":"https:\/\/pbs.twimg.com\/profile_images\/1037099983252738055\/9t5FFbFx_normal.jpg","profile_banner_url":"https:\/\/pbs.twimg.com\/profile_banners\/2275915428\/1536359802","default_profile":false,"default_profile_image":false,"following":null,"follow_request_sent":null,"notifications":null},"geo":null,"coordinates":null,"place":null,"contributors":null,"is_quote_status":false,"quote_count":0,"reply_count":1,"retweet_count":1,"favorite_count":2,"entities":{"hashtags":[],"urls":[],"user_mentions":[{"screen_name":"samalvesmusic","name":"Sam Alves \u2764\ufe0f\ud83e\udde1\ud83d\udc9b\ud83d\udc9a\ud83d\udc99\ud83d\udc9c","id":855216613,"id_str":"855216613","indices":[0,14]}],"symbols":[]},"favorited":false,"retweeted":false,"filter_level":"low","lang":"pt"},"is_quote_status":false,"quote_count":0,"reply_count":0,"retweet_count":0,"favorite_count":0,"entities":{"hashtags":[],"urls":[],"user_mentions":[{"screen_name":"SuelyLima17","name":"Suely Lima","id":2275915428,"id_str":"2275915428","indices":[3,15]},{"screen_name":"samalvesmusic","name":"Sam Alves \u2764\ufe0f\ud83e\udde1\ud83d\udc9b\ud83d\udc9a\ud83d\udc99\ud83d\udc9c","id":855216613,"id_str":"855216613","indices":[17,31]}],"symbols":[]},"favorited":false,"retweeted":false,"filter_level":"low","lang":"pt","timestamp_ms":"1540259751339"}
{"created_at":"Tue Oct 23 01:55:51 +0000 2018","id":1054551948198846466,"id_str":"1054551948198846466","text":"RT @NickJFuentes: HELLO EPIC DEPARTMENT?? YES IT\u2019S ME AGAI- https:\/\/t.co\/l6Smw49dsm","source":"\u003ca href=\"http:\/\/twitter.com\" rel=\"nofollow\"\u003eTwitter Web Client\u003c\/a\u003e","truncated":false,"in_reply_to_status_id":null,"in_reply_to_status_id_str":null,"in_reply_to_user_id":null,"in_reply_to_user_id_str":null,"in_reply_to_screen_name":null,"user":{"id":1040056945791696896,"id_str":"1040056945791696896","name":"The(Punished)GibbonGuy","screen_name":"PunishedGibbon","location":null,"url":null,"description":"One cool guy. Avatar courtesy of @devilandmarysue","translator_type":"none","protected":false,"verified":false,"followers_count":985,"friends_count":603,"listed_count":3,"favourites_count":5258,"statuses_count":1208,"created_at":"Thu Sep 13 01:57:54 +0000 2018","utc_offset":null,"time_zone":null,"geo_enabled":false,"lang":"en","contributors_enabled":false,"is_translator":false,"profile_background_color":"F5F8FA","profile_background_image_url":"","profile_background_image_url_https":"","profile_background_tile":false,"profile_link_color":"1DA1F2","profile_sidebar_border_color":"C0DEED","profile_sidebar_fill_color":"DDEEF6","profile_text_color":"333333","profile_use_background_image":true,"profile_image_url":"http:\/\/pbs.twimg.com\/profile_images\/1040057068399382528\/9nG2tDLo_normal.jpg","profile_image_url_https":"https:\/\/pbs.twimg.com\/profile_images\/1040057068399382528\/9nG2tDLo_normal.jpg","profile_banner_url":"https:\/\/pbs.twimg.com\/profile_banners\/1040056945791696896\/1536897713","default_profile":true,"default_profile_image":false,"following":null,"follow_request_sent":null,"notifications":null},"geo":null,"coordinates":null,"place":null,"contributors":null,"retweeted_status":{"created_at":"Tue Oct 23 01:10:11 +0000 2018","id":1054540453251637254,"id_str":"1054540453251637254","text":"HELLO EPIC DEPARTMENT?? YES IT\u2019S ME AGAI- https:\/\/t.co\/l6Smw49dsm","display_text_range":[0,41],"source":"\u003ca href=\"http:\/\/twitter.com\/download\/iphone\" rel=\"nofollow\"\u003eTwitter for iPhone\u003c\/a\u003e","truncated":false,"in_reply_to_status_id":null,"in_reply_to_status_id_str":null,"in_reply_to_user_id":null,"in_reply_to_user_id_str":null,"in_reply_to_screen_name":null,"user":{"id":2442888666,"id_str":"2442888666","name":"Nicholas J. Fuentes","screen_name":"NickJFuentes","location":"Chicago, IL","url":"http:\/\/NicholasJFuentes.com","description":"Host of America First \u2022 Paleoconservative \u2022 Nationalist \u2022 Catholic","translator_type":"none","protected":false,"verified":true,"followers_count":29323,"friends_count":508,"listed_count":464,"favourites_count":102084,"statuses_count":13034,"created_at":"Mon Apr 14 00:27:45 +0000 2014","utc_offset":null,"time_zone":null,"geo_enabled":true,"lang":"en","contributors_enabled":false,"is_translator":false,"profile_background_color":"000000","profile_background_image_url":"http:\/\/abs.twimg.com\/images\/themes\/theme1\/bg.png","profile_background_image_url_https":"https:\/\/abs.twimg.com\/images\/themes\/theme1\/bg.png","profile_background_tile":false,"profile_link_color":"1B95E0","profile_sidebar_border_color":"000000","profile_sidebar_fill_color":"000000","profile_text_color":"000000","profile_use_background_image":false,"profile_image_url":"http:\/\/pbs.twimg.com\/profile_images\/885086017623130114\/KLyK4cVD_normal.jpg","profile_image_url_https":"https:\/\/pbs.twimg.com\/profile_images\/885086017623130114\/KLyK4cVD_normal.jpg","profile_banner_url":"https:\/\/pbs.twimg.com\/profile_banners\/2442888666\/1539932955","default_profile":false,"default_profile_image":false,"following":null,"follow_request_sent":null,"notifications":null},"geo":null,"coordinates":null,"place":null,"contributors":null,"quoted_status_id":1054530899914698753,"quoted_status_id_str":"1054530899914698753","quoted_status":{"created_at":"Tue Oct 23 00:32:13 +0000 2018","id":1054530899914698753,"id_str":"1054530899914698753","text":".@POTUS: \"I'm a nationalist.\" https:\/\/t.co\/OiPPIlVdUP https:\/\/t.co\/yuF0lU5qYS","display_text_range":[0,53],"source":"\u003ca href=\"https:\/\/studio.twitter.com\" rel=\"nofollow\"\u003eMedia Studio\u003c\/a\u003e","truncated":false,"in_reply_to_status_id":null,"in_reply_to_status_id_str":null,"in_reply_to_user_id":null,"in_reply_to_user_id_str":null,"in_reply_to_screen_name":null,"user":{"id":1367531,"id_str":"1367531","name":"Fox News","screen_name":"FoxNews","location":"U.S.A.","url":"http:\/\/www.foxnews.com","description":"America\u2019s Strongest Primetime Lineup Anywhere! Follow America's #1 cable news network, delivering you breaking news, insightful analysis, and must-see videos.","translator_type":"regular","protected":false,"verified":true,"followers_count":18200880,"friends_count":398,"listed_count":64783,"favourites_count":0,"statuses_count":415582,"created_at":"Sat Mar 17 19:01:26 +0000 2007","utc_offset":null,"time_zone":null,"geo_enabled":true,"lang":"en","contributors_enabled":false,"is_translator":false,"profile_background_color":"0E2331","profile_background_image_url":"http:\/\/abs.twimg.com\/images\/themes\/theme1\/bg.png","profile_background_image_url_https":"https:\/\/abs.twimg.com\/images\/themes\/theme1\/bg.png","profile_background_tile":false,"profile_link_color":"183A52","profile_sidebar_border_color":"FFFFFF","profile_sidebar_fill_color":"F4F4F4","profile_text_color":"000000","profile_use_background_image":true,"profile_image_url":"http:\/\/pbs.twimg.com\/profile_images\/918480715158716419\/4X8oCbge_normal.jpg","profile_image_url_https":"https:\/\/pbs.twimg.com\/profile_images\/918480715158716419\/4X8oCbge_normal.jpg","profile_banner_url":"https:\/\/pbs.twimg.com\/profile_banners\/1367531\/1492649996","default_profile":false,"default_profile_image":false,"following":null,"follow_request_sent":null,"notifications":null},"geo":null,"coordinates":null,"place":null,"contributors":null,"is_quote_status":false,"quote_count":146,"reply_count":409,"retweet_count":633,"favorite_count":2095,"entities":{"hashtags":[],"urls":[{"url":"https:\/\/t.co\/OiPPIlVdUP","expanded_url":"http:\/\/fxn.ws\/2OFFya3","display_url":"fxn.ws\/2OFFya3","indices":[30,53]}],"user_mentions":[{"screen_name":"POTUS","name":"President Trump","id":822215679726100480,"id_str":"822215679726100480","indices":[1,7]}],"symbols":[],"media":[{"id":1054529580785168384,"id_str":"1054529580785168384","indices":[54,77],"additional_media_info":{"title":"","description":"","embeddable":true,"monetizable":true},"media_url":"http:\/\/pbs.twimg.com\/media\/DqJxPFBXcAA6c3w.jpg","media_url_https":"https:\/\/pbs.twimg.com\/media\/DqJxPFBXcAA6c3w.jpg","url":"https:\/\/t.co\/yuF0lU5qYS","display_url":"pic.twitter.com\/yuF0lU5qYS","expanded_url":"https:\/\/twitter.com\/FoxNews\/status\/1054530899914698753\/video\/1","type":"photo","sizes":{"thumb":{"w":150,"h":150,"resize":"crop"},"large":{"w":640,"h":360,"resize":"fit"},"medium":{"w":640,"h":360,"resize":"fit"},"small":{"w":640,"h":360,"resize":"fit"}}}]},"extended_entities":{"media":[{"id":1054529580785168384,"id_str":"1054529580785168384","indices":[54,77],"additional_media_info":{"title":"","description":"","embeddable":true,"monetizable":true},"media_url":"http:\/\/pbs.twimg.com\/media\/DqJxPFBXcAA6c3w.jpg","media_url_https":"https:\/\/pbs.twimg.com\/media\/DqJxPFBXcAA6c3w.jpg","url":"https:\/\/t.co\/yuF0lU5qYS","display_url":"pic.twitter.com\/yuF0lU5qYS","expanded_url":"https:\/\/twitter.com\/FoxNews\/status\/1054530899914698753\/video\/1","type":"video","video_info":{"aspect_ratio":[16,9],"duration_millis":22222,"variants":[{"bitrate":2176000,"content_type":"video\/mp4","url":"https:\/\/video.twimg.com\/amplify_video\/1054529580785168384\/vid\/1280x720\/4mkJkL5r70x48CaF.mp4?tag=8"},{"bitrate":832000,"content_type":"video\/mp4","url":"https:\/\/video.twimg.com\/amplify_video\/1054529580785168384\/vid\/640x360\/K2JmlUoSW13StYUj.mp4?tag=8"},{"bitrate":288000,"content_type":"video\/mp4","url":"https:\/\/video.twimg.com\/amplify_video\/1054529580785168384\/vid\/320x180\/SW9_8RNVzentuvMf.mp4?tag=8"},{"content_type":"application\/x-mpegURL","url":"https:\/\/video.twimg.com\/amplify_video\/1054529580785168384\/pl\/tXm_mqVcMJpsgAby.m3u8?tag=8"}]},"sizes":{"thumb":{"w":150,"h":150,"resize":"crop"},"large":{"w":640,"h":360,"resize":"fit"},"medium":{"w":640,"h":360,"resize":"fit"},"small":{"w":640,"h":360,"resize":"fit"}}}]},"favorited":false,"retweeted":false,"possibly_sensitive":false,"filter_level":"low","lang":"en"},"quoted_status_permalink":{"url":"https:\/\/t.co\/l6Smw49dsm","expanded":"https:\/\/twitter.com\/foxnews\/status\/1054530899914698753","display":"twitter.com\/foxnews\/status\u2026"},"is_quote_status":true,"quote_count":0,"reply_count":13,"retweet_count":70,"favorite_count":320,"entities":{"hashtags":[],"urls":[{"url":"https:\/\/t.co\/l6Smw49dsm","expanded_url":"https:\/\/twitter.com\/foxnews\/status\/1054530899914698753","display_url":"twitter.com\/foxnews\/status\u2026","indices":[42,65]}],"user_mentions":[],"symbols":[]},"favorited":false,"retweeted":false,"possibly_sensitive":false,"filter_level":"low","lang":"en"},"quoted_status_id":1054530899914698753,"quoted_status_id_str":"1054530899914698753","quoted_status":{"created_at":"Tue Oct 23 00:32:13 +0000 2018","id":1054530899914698753,"id_str":"1054530899914698753","text":".@POTUS: \"I'm a nationalist.\" https:\/\/t.co\/OiPPIlVdUP https:\/\/t.co\/yuF0lU5qYS","display_text_range":[0,53],"source":"\u003ca href=\"https:\/\/studio.twitter.com\" rel=\"nofollow\"\u003eMedia Studio\u003c\/a\u003e","truncated":false,"in_reply_to_status_id":null,"in_reply_to_status_id_str":null,"in_reply_to_user_id":null,"in_reply_to_user_id_str":null,"in_reply_to_screen_name":null,"user":{"id":1367531,"id_str":"1367531","name":"Fox News","screen_name":"FoxNews","location":"U.S.A.","url":"http:\/\/www.foxnews.com","description":"America\u2019s Strongest Primetime Lineup Anywhere! Follow America's #1 cable news network, delivering you breaking news, insightful analysis, and must-see videos.","translator_type":"regular","protected":false,"verified":true,"followers_count":18200880,"friends_count":398,"listed_count":64783,"favourites_count":0,"statuses_count":415582,"created_at":"Sat Mar 17 19:01:26 +0000 2007","utc_offset":null,"time_zone":null,"geo_enabled":true,"lang":"en","contributors_enabled":false,"is_translator":false,"profile_background_color":"0E2331","profile_background_image_url":"http:\/\/abs.twimg.com\/images\/themes\/theme1\/bg.png","profile_background_image_url_https":"https:\/\/abs.twimg.com\/images\/themes\/theme1\/bg.png","profile_background_tile":false,"profile_link_color":"183A52","profile_sidebar_border_color":"FFFFFF","profile_sidebar_fill_color":"F4F4F4","profile_text_color":"000000","profile_use_background_image":true,"profile_image_url":"http:\/\/pbs.twimg.com\/profile_images\/918480715158716419\/4X8oCbge_normal.jpg","profile_image_url_https":"https:\/\/pbs.twimg.com\/profile_images\/918480715158716419\/4X8oCbge_normal.jpg","profile_banner_url":"https:\/\/pbs.twimg.com\/profile_banners\/1367531\/1492649996","default_profile":false,"default_profile_image":false,"following":null,"follow_request_sent":null,"notifications":null},"geo":null,"coordinates":null,"place":null,"contributors":null,"is_quote_status":false,"quote_count":146,"reply_count":409,"retweet_count":633,"favorite_count":2095,"entities":{"hashtags":[],"urls":[{"url":"https:\/\/t.co\/OiPPIlVdUP","expanded_url":"http:\/\/fxn.ws\/2OFFya3","display_url":"fxn.ws\/2OFFya3","indices":[30,53]}],"user_mentions":[{"screen_name":"POTUS","name":"President Trump","id":822215679726100480,"id_str":"822215679726100480","indices":[1,7]}],"symbols":[],"media":[{"id":1054529580785168384,"id_str":"1054529580785168384","indices":[54,77],"additional_media_info":{"title":"","description":"","embeddable":true,"monetizable":true},"media_url":"http:\/\/pbs.twimg.com\/media\/DqJxPFBXcAA6c3w.jpg","media_url_https":"https:\/\/pbs.twimg.com\/media\/DqJxPFBXcAA6c3w.jpg","url":"https:\/\/t.co\/yuF0lU5qYS","display_url":"pic.twitter.com\/yuF0lU5qYS","expanded_url":"https:\/\/twitter.com\/FoxNews\/status\/1054530899914698753\/video\/1","type":"photo","sizes":{"thumb":{"w":150,"h":150,"resize":"crop"},"large":{"w":640,"h":360,"resize":"fit"},"medium":{"w":640,"h":360,"resize":"fit"},"small":{"w":640,"h":360,"resize":"fit"}}}]},"extended_entities":{"media":[{"id":1054529580785168384,"id_str":"1054529580785168384","indices":[54,77],"additional_media_info":{"title":"","description":"","embeddable":true,"monetizable":true},"media_url":"http:\/\/pbs.twimg.com\/media\/DqJxPFBXcAA6c3w.jpg","media_url_https":"https:\/\/pbs.twimg.com\/media\/DqJxPFBXcAA6c3w.jpg","url":"https:\/\/t.co\/yuF0lU5qYS","display_url":"pic.twitter.com\/yuF0lU5qYS","expanded_url":"https:\/\/twitter.com\/FoxNews\/status\/1054530899914698753\/video\/1","type":"video","video_info":{"aspect_ratio":[16,9],"duration_millis":22222,"variants":[{"bitrate":2176000,"content_type":"video\/mp4","url":"https:\/\/video.twimg.com\/amplify_video\/1054529580785168384\/vid\/1280x720\/4mkJkL5r70x48CaF.mp4?tag=8"},{"bitrate":832000,"content_type":"video\/mp4","url":"https:\/\/video.twimg.com\/amplify_video\/1054529580785168384\/vid\/640x360\/K2JmlUoSW13StYUj.mp4?tag=8"},{"bitrate":288000,"content_type":"video\/mp4","url":"https:\/\/video.twimg.com\/amplify_video\/1054529580785168384\/vid\/320x180\/SW9_8RNVzentuvMf.mp4?tag=8"},{"content_type":"application\/x-mpegURL","url":"https:\/\/video.twimg.com\/amplify_video\/1054529580785168384\/pl\/tXm_mqVcMJpsgAby.m3u8?tag=8"}]},"sizes":{"thumb":{"w":150,"h":150,"resize":"crop"},"large":{"w":640,"h":360,"resize":"fit"},"medium":{"w":640,"h":360,"resize":"fit"},"small":{"w":640,"h":360,"resize":"fit"}}}]},"favorited":false,"retweeted":false,"possibly_sensitive":false,"filter_level":"low","lang":"en"},"quoted_status_permalink":{"url":"https:\/\/t.co\/l6Smw49dsm","expanded":"https:\/\/twitter.com\/foxnews\/status\/1054530899914698753","display":"twitter.com\/foxnews\/status\u2026"},"is_quote_status":true,"quote_count":0,"reply_count":0,"retweet_count":0,"favorite_count":0,"entities":{"hashtags":[],"urls":[{"url":"https:\/\/t.co\/l6Smw49dsm","expanded_url":"https:\/\/twitter.com\/foxnews\/status\/1054530899914698753","display_url":"twitter.com\/foxnews\/status\u2026","indices":[60,83]}],"user_mentions":[{"screen_name":"NickJFuentes","name":"Nicholas J. Fuentes","id":2442888666,"id_str":"2442888666","indices":[3,16]}],"symbols":[]},"favorited":false,"retweeted":false,"possibly_sensitive":false,"filter_level":"low","lang":"en","timestamp_ms":"1540259751735"}
{"created_at":"Tue Oct 23 01:55:52 +0000 2018","id":1054551949415211013,"id_str":"1054551949415211013","text":"@gewozahiweg Hello, my name is Sergei, I am a founder of private trading community \u00ab10x club\u00bb. Now we opened our do\u2026 https:\/\/t.co\/CC5NDKU3ou","display_text_range":[13,140],"source":"\u003ca href=\"http:\/\/twitter.com\/download\/android\" rel=\"nofollow\"\u003eTwitter for Android\u003c\/a\u003e","truncated":true,"in_reply_to_status_id":1054551765113221120,"in_reply_to_status_id_str":"1054551765113221120","in_reply_to_user_id":2453856685,"in_reply_to_user_id_str":"2453856685","in_reply_to_screen_name":"gewozahiweg","user":{"id":1046754877630795776,"id_str":"1046754877630795776","name":"Dana","screen_name":"Dana68693114","location":null,"url":null,"description":"Receive daily signals and portfolio tips from a veteran crypto trader and become part of a strong Telegram crypto trading group. https:\/\/t.me\/symetraplatform","translator_type":"none","protected":false,"verified":false,"followers_count":0,"friends_count":0,"listed_count":0,"favourites_count":0,"statuses_count":43,"created_at":"Mon Oct 01 13:33:05 +0000 2018","utc_offset":null,"time_zone":null,"geo_enabled":false,"lang":"en","contributors_enabled":false,"is_translator":false,"profile_background_color":"F5F8FA","profile_background_image_url":"","profile_background_image_url_https":"","profile_background_tile":false,"profile_link_color":"1DA1F2","profile_sidebar_border_color":"C0DEED","profile_sidebar_fill_color":"DDEEF6","profile_text_color":"333333","profile_use_background_image":true,"profile_image_url":"http:\/\/pbs.twimg.com\/profile_images\/1046756509256945665\/YsS-EsDq_normal.jpg","profile_image_url_https":"https:\/\/pbs.twimg.com\/profile_images\/1046756509256945665\/YsS-EsDq_normal.jpg","profile_banner_url":"https:\/\/pbs.twimg.com\/profile_banners\/1046754877630795776\/1540228719","default_profile":true,"default_profile_image":false,"following":null,"follow_request_sent":null,"notifications":null},"geo":null,"coordinates":null,"place":null,"contributors":null,"is_quote_status":false,"extended_tweet":{"full_text":"@gewozahiweg Hello, my name is Sergei, I am a founder of private trading community \u00ab10x club\u00bb. Now we opened our doors for 100 people, join and get Intense signals for new exchanges \u27a1 https:\/\/t.co\/Kt4mruvGT9\n\n$LTC #Cardano \n\n\u2b55 641180267","display_text_range":[13,236],"entities":{"hashtags":[{"text":"Cardano","indices":[214,222]}],"urls":[{"url":"https:\/\/t.co\/Kt4mruvGT9","expanded_url":"https:\/\/t.me\/symetraplatform","display_url":"t.me\/symetraplatform","indices":[184,207]}],"user_mentions":[{"screen_name":"gewozahiweg","name":"Ulysses Boerderman","id":2453856685,"id_str":"2453856685","indices":[0,12]}],"symbols":[{"text":"LTC","indices":[209,213]}]}},"quote_count":0,"reply_count":0,"retweet_count":0,"favorite_count":0,"entities":{"hashtags":[],"urls":[{"url":"https:\/\/t.co\/CC5NDKU3ou","expanded_url":"https:\/\/twitter.com\/i\/web\/status\/1054551949415211013","display_url":"twitter.com\/i\/web\/status\/1\u2026","indices":[117,140]}],"user_mentions":[{"screen_name":"gewozahiweg","name":"Ulysses Boerderman","id":2453856685,"id_str":"2453856685","indices":[0,12]}],"symbols":[]},"favorited":false,"retweeted":false,"possibly_sensitive":false,"filter_level":"low","lang":"en","timestamp_ms":"1540259752025"}
{"created_at":"Tue Oct 23 01:55:52 +0000 2018","id":1054551949448642561,"id_str":"1054551949448642561","text":"@ULTIMATERPE hello oppa! mind to notice your labelmate? \u314b\u314b\u314b\u314b","display_text_range":[13,60],"source":"\u003ca href=\"http:\/\/twitter.com\/download\/android\" rel=\"nofollow\"\u003eTwitter for Android\u003c\/a\u003e","truncated":false,"in_reply_to_status_id":1054551764819632128,"in_reply_to_status_id_str":"1054551764819632128","in_reply_to_user_id":861831883067465728,"in_reply_to_user_id_str":"861831883067465728","in_reply_to_screen_name":"ULTIMATERPE","user":{"id":965920080826548225,"id_str":"965920080826548225","name":"\uc608\ub9ac\ud83d\udc27","screen_name":"rvbabyerim_","location":null,"url":null,"description":"[RP] \ud83d\udc8c \ub808\ub4dc\ubca8\ubcb4's baby magnae, kim yerim is the name.","translator_type":"none","protected":false,"verified":false,"followers_count":352,"friends_count":376,"listed_count":2,"favourites_count":25,"statuses_count":784,"created_at":"Tue Feb 20 12:04:27 +0000 2018","utc_offset":null,"time_zone":null,"geo_enabled":false,"lang":"id","contributors_enabled":false,"is_translator":false,"profile_background_color":"F5F8FA","profile_background_image_url":"","profile_background_image_url_https":"","profile_background_tile":false,"profile_link_color":"1DA1F2","profile_sidebar_border_color":"C0DEED","profile_sidebar_fill_color":"DDEEF6","profile_text_color":"333333","profile_use_background_image":true,"profile_image_url":"http:\/\/pbs.twimg.com\/profile_images\/1051130073758097408\/soZJ34XP_normal.jpg","profile_image_url_https":"https:\/\/pbs.twimg.com\/profile_images\/1051130073758097408\/soZJ34XP_normal.jpg","profile_banner_url":"https:\/\/pbs.twimg.com\/profile_banners\/965920080826548225\/1539443913","default_profile":true,"default_profile_image":false,"following":null,"follow_request_sent":null,"notifications":null},"geo":null,"coordinates":null,"place":null,"contributors":null,"is_quote_status":false,"quote_count":0,"reply_count":0,"retweet_count":0,"favorite_count":0,"entities":{"hashtags":[],"urls":[],"user_mentions":[{"screen_name":"ULTIMATERPE","name":"\ud83c\udf38","id":861831883067465728,"id_str":"861831883067465728","indices":[0,12]}],"symbols":[]},"favorited":false,"retweeted":false,"filter_level":"low","lang":"en","timestamp_ms":"1540259752033"}
{"created_at":"Tue Oct 23 01:55:52 +0000 2018","id":1054551951025725440,"id_str":"1054551951025725440","text":"RT @sadlilthingx: my friend: hey u ok\n\nme, in a depressive episode:\n\nthem: hello\n\nme, 8 days later: ahsjksk my bad yeah im fine!!! how are\u2026","source":"\u003ca href=\"http:\/\/twitter.com\/download\/iphone\" rel=\"nofollow\"\u003eTwitter for iPhone\u003c\/a\u003e","truncated":false,"in_reply_to_status_id":null,"in_reply_to_status_id_str":null,"in_reply_to_user_id":null,"in_reply_to_user_id_str":null,"in_reply_to_screen_name":null,"user":{"id":2411151661,"id_str":"2411151661","name":"NaniV.","screen_name":"nvargasss","location":null,"url":null,"description":null,"translator_type":"none","protected":false,"verified":false,"followers_count":290,"friends_count":412,"listed_count":0,"favourites_count":2715,"statuses_count":11448,"created_at":"Tue Mar 25 15:01:33 +0000 2014","utc_offset":null,"time_zone":null,"geo_enabled":true,"lang":"en","contributors_enabled":false,"is_translator":false,"profile_background_color":"C0DEED","profile_background_image_url":"http:\/\/abs.twimg.com\/images\/themes\/theme1\/bg.png","profile_background_image_url_https":"https:\/\/abs.twimg.com\/images\/themes\/theme1\/bg.png","profile_background_tile":false,"profile_link_color":"DB11BD","profile_sidebar_border_color":"C0DEED","profile_sidebar_fill_color":"DDEEF6","profile_text_color":"333333","profile_use_background_image":true,"profile_image_url":"http:\/\/pbs.twimg.com\/profile_images\/1031782395328921601\/Y2XjQ6tN_normal.jpg","profile_image_url_https":"https:\/\/pbs.twimg.com\/profile_images\/1031782395328921601\/Y2XjQ6tN_normal.jpg","profile_banner_url":"https:\/\/pbs.twimg.com\/profile_banners\/2411151661\/1535162539","default_profile":false,"default_profile_image":false,"following":null,"follow_request_sent":null,"notifications":null},"geo":null,"coordinates":null,"place":null,"contributors":null,"retweeted_status":{"created_at":"Sun Oct 21 19:10:43 +0000 2018","id":1054087605942394880,"id_str":"1054087605942394880","text":"my friend: hey u ok\n\nme, in a depressive episode:\n\nthem: hello\n\nme, 8 days later: ahsjksk my bad yeah im fine!!! how are YOU tho??!!","source":"\u003ca href=\"http:\/\/twitter.com\/download\/iphone\" rel=\"nofollow\"\u003eTwitter for iPhone\u003c\/a\u003e","truncated":false,"in_reply_to_status_id":null,"in_reply_to_status_id_str":null,"in_reply_to_user_id":null,"in_reply_to_user_id_str":null,"in_reply_to_screen_name":null,"user":{"id":1015691477391994880,"id_str":"1015691477391994880","name":"asia","screen_name":"sadlilthingx","location":"DBC \ud83d\udc94","url":"http:\/\/instagram.com\/asiaisdead","description":null,"translator_type":"none","protected":false,"verified":false,"followers_count":1213,"friends_count":809,"listed_count":18,"favourites_count":1119,"statuses_count":258,"created_at":"Sat Jul 07 20:18:13 +0000 2018","utc_offset":null,"time_zone":null,"geo_enabled":false,"lang":"en","contributors_enabled":false,"is_translator":false,"profile_background_color":"F5F8FA","profile_background_image_url":"","profile_background_image_url_https":"","profile_background_tile":false,"profile_link_color":"1DA1F2","profile_sidebar_border_color":"C0DEED","profile_sidebar_fill_color":"DDEEF6","profile_text_color":"333333","profile_use_background_image":true,"profile_image_url":"http:\/\/pbs.twimg.com\/profile_images\/1053716355004948480\/1ZL09iPv_normal.jpg","profile_image_url_https":"https:\/\/pbs.twimg.com\/profile_images\/1053716355004948480\/1ZL09iPv_normal.jpg","profile_banner_url":"https:\/\/pbs.twimg.com\/profile_banners\/1015691477391994880\/1537007809","default_profile":true,"default_profile_image":false,"following":null,"follow_request_sent":null,"notifications":null},"geo":null,"coordinates":null,"place":null,"contributors":null,"is_quote_status":false,"quote_count":1780,"reply_count":284,"retweet_count":42094,"favorite_count":176698,"entities":{"hashtags":[],"urls":[],"user_mentions":[],"symbols":[]},"favorited":false,"retweeted":false,"filter_level":"low","lang":"en"},"is_quote_status":false,"quote_count":0,"reply_count":0,"retweet_count":0,"favorite_count":0,"entities":{"hashtags":[],"urls":[],"user_mentions":[{"screen_name":"sadlilthingx","name":"asia","id":1015691477391994880,"id_str":"1015691477391994880","indices":[3,16]}],"symbols":[]},"favorited":false,"retweeted":false,"filter_level":"low","lang":"en","timestamp_ms":"1540259752409"}
{"created_at":"Tue Oct 23 01:55:53 +0000 2018","id":1054551953689075712,"id_str":"1054551953689075712","text":"RT @S_Marguerite: Hello, here's my cover for #FaithTheDreamside #3 published by #ValiantComics on a scenario by @Jody_Houser there maybe a\u2026","source":"\u003ca href=\"http:\/\/twitter.com\/download\/iphone\" rel=\"nofollow\"\u003eTwitter for iPhone\u003c\/a\u003e","truncated":false,"in_reply_to_status_id":null,"in_reply_to_status_id_str":null,"in_reply_to_user_id":null,"in_reply_to_user_id_str":null,"in_reply_to_screen_name":null,"user":{"id":18076440,"id_str":"18076440","name":"\ud83d\udc80\ud83d\udda4v\u00e9rONIque emma houxbois\ud83d\udda4\ud83d\udc80","screen_name":"EmmaHouxbois","location":"transmyscira","url":"http:\/\/www.comicosity.com","description":"feral drag baby. art hoe. wonder woman enthusiast. transmyscira for @comicosity. @enzuigirli GM. http:\/\/ko-fi.com\/veroniqueemmahouxbois","translator_type":"none","protected":false,"verified":false,"followers_count":1563,"friends_count":499,"listed_count":95,"favourites_count":34670,"statuses_count":89525,"created_at":"Fri Dec 12 14:02:49 +0000 2008","utc_offset":null,"time_zone":null,"geo_enabled":true,"lang":"en","contributors_enabled":false,"is_translator":false,"profile_background_color":"000000","profile_background_image_url":"http:\/\/abs.twimg.com\/images\/themes\/theme1\/bg.png","profile_background_image_url_https":"https:\/\/abs.twimg.com\/images\/themes\/theme1\/bg.png","profile_background_tile":true,"profile_link_color":"A8A8A8","profile_sidebar_border_color":"A80000","profile_sidebar_fill_color":"000000","profile_text_color":"990808","profile_use_background_image":true,"profile_image_url":"http:\/\/pbs.twimg.com\/profile_images\/1046278828362878976\/pvaZaFbt_normal.jpg","profile_image_url_https":"https:\/\/pbs.twimg.com\/profile_images\/1046278828362878976\/pvaZaFbt_normal.jpg","profile_banner_url":"https:\/\/pbs.twimg.com\/profile_banners\/18076440\/1537511123","default_profile":false,"default_profile_image":false,"following":null,"follow_request_sent":null,"notifications":null},"geo":null,"coordinates":null,"place":null,"contributors":null,"retweeted_status":{"created_at":"Mon Oct 22 17:46:55 +0000 2018","id":1054428902725206016,"id_str":"1054428902725206016","text":"Hello, here's my cover for #FaithTheDreamside #3 published by #ValiantComics on a scenario by @Jody_Houser there ma\u2026 https:\/\/t.co\/OqLANXqGI0","display_text_range":[0,140],"source":"\u003ca href=\"http:\/\/twitter.com\" rel=\"nofollow\"\u003eTwitter Web Client\u003c\/a\u003e","truncated":true,"in_reply_to_status_id":null,"in_reply_to_status_id_str":null,"in_reply_to_user_id":null,"in_reply_to_user_id_str":null,"in_reply_to_screen_name":null,"user":{"id":112990433,"id_str":"112990433","name":"Marguerite Sauvage","screen_name":"S_Marguerite","location":"Paris, France","url":"http:\/\/www.margueritesauvage.com","description":"Illustrator, concept artist & comicbook artist (Faith, DC Bombshells, Red Sonja, Civil War, Thor, Adventure Time, etc). I love otters, good food and books.","translator_type":"none","protected":false,"verified":false,"followers_count":14130,"friends_count":1335,"listed_count":410,"favourites_count":10765,"statuses_count":6000,"created_at":"Wed Feb 10 10:15:23 +0000 2010","utc_offset":null,"time_zone":null,"geo_enabled":true,"lang":"en","contributors_enabled":false,"is_translator":false,"profile_background_color":"FFFFFF","profile_background_image_url":"http:\/\/abs.twimg.com\/images\/themes\/theme1\/bg.png","profile_background_image_url_https":"https:\/\/abs.twimg.com\/images\/themes\/theme1\/bg.png","profile_background_tile":true,"profile_link_color":"0084B4","profile_sidebar_border_color":"FFFFFF","profile_sidebar_fill_color":"DDEEF6","profile_text_color":"333333","profile_use_background_image":true,"profile_image_url":"http:\/\/pbs.twimg.com\/profile_images\/553939106770604036\/KJjKdtxL_normal.jpeg","profile_image_url_https":"https:\/\/pbs.twimg.com\/profile_images\/553939106770604036\/KJjKdtxL_normal.jpeg","profile_banner_url":"https:\/\/pbs.twimg.com\/profile_banners\/112990433\/1399991855","default_profile":false,"default_profile_image":false,"following":null,"follow_request_sent":null,"notifications":null},"geo":null,"coordinates":null,"place":null,"contributors":null,"is_quote_status":false,"extended_tweet":{"full_text":"Hello, here's my cover for #FaithTheDreamside #3 published by #ValiantComics on a scenario by @Jody_Houser there maybe a wink to #SailorMoon in this one ;) #FlyLikeFaith #DigitalArt #Illustration #Comics #CoverArt #illustrationartist #BodyPositive https:\/\/t.co\/sJJOfsOOHt","display_text_range":[0,247],"entities":{"hashtags":[{"text":"FaithTheDreamside","indices":[27,45]},{"text":"ValiantComics","indices":[62,76]},{"text":"SailorMoon","indices":[129,140]},{"text":"FlyLikeFaith","indices":[156,169]},{"text":"DigitalArt","indices":[170,181]},{"text":"Illustration","indices":[182,195]},{"text":"Comics","indices":[196,203]},{"text":"CoverArt","indices":[204,213]},{"text":"illustrationartist","indices":[214,233]},{"text":"BodyPositive","indices":[234,247]}],"urls":[],"user_mentions":[{"screen_name":"Jody_Houser","name":"The Haunting of Jody Houser \u2712\ufe0f\ud83d\uddef\ufe0f\ud83c\udfb2","id":15566406,"id_str":"15566406","indices":[94,106]}],"symbols":[],"media":[{"id":1054428095699083264,"id_str":"1054428095699083264","indices":[248,271],"media_url":"http:\/\/pbs.twimg.com\/media\/DqIUxDVV4AAU8Hd.jpg","media_url_https":"https:\/\/pbs.twimg.com\/media\/DqIUxDVV4AAU8Hd.jpg","url":"https:\/\/t.co\/sJJOfsOOHt","display_url":"pic.twitter.com\/sJJOfsOOHt","expanded_url":"https:\/\/twitter.com\/S_Marguerite\/status\/1054428902725206016\/photo\/1","type":"photo","sizes":{"large":{"w":687,"h":1044,"resize":"fit"},"thumb":{"w":150,"h":150,"resize":"crop"},"medium":{"w":687,"h":1044,"resize":"fit"},"small":{"w":447,"h":680,"resize":"fit"}}}]},"extended_entities":{"media":[{"id":1054428095699083264,"id_str":"1054428095699083264","indices":[248,271],"media_url":"http:\/\/pbs.twimg.com\/media\/DqIUxDVV4AAU8Hd.jpg","media_url_https":"https:\/\/pbs.twimg.com\/media\/DqIUxDVV4AAU8Hd.jpg","url":"https:\/\/t.co\/sJJOfsOOHt","display_url":"pic.twitter.com\/sJJOfsOOHt","expanded_url":"https:\/\/twitter.com\/S_Marguerite\/status\/1054428902725206016\/photo\/1","type":"photo","sizes":{"large":{"w":687,"h":1044,"resize":"fit"},"thumb":{"w":150,"h":150,"resize":"crop"},"medium":{"w":687,"h":1044,"resize":"fit"},"small":{"w":447,"h":680,"resize":"fit"}}}]}},"quote_count":5,"reply_count":5,"retweet_count":23,"favorite_count":94,"entities":{"hashtags":[{"text":"FaithTheDreamside","indices":[27,45]},{"text":"ValiantComics","indices":[62,76]}],"urls":[{"url":"https:\/\/t.co\/OqLANXqGI0","expanded_url":"https:\/\/twitter.com\/i\/web\/status\/1054428902725206016","display_url":"twitter.com\/i\/web\/status\/1\u2026","indices":[117,140]}],"user_mentions":[{"screen_name":"Jody_Houser","name":"The Haunting of Jody Houser \u2712\ufe0f\ud83d\uddef\ufe0f\ud83c\udfb2","id":15566406,"id_str":"15566406","indices":[94,106]}],"symbols":[]},"favorited":false,"retweeted":false,"possibly_sensitive":false,"filter_level":"low","lang":"en"},"is_quote_status":false,"quote_count":0,"reply_count":0,"retweet_count":0,"favorite_count":0,"entities":{"hashtags":[{"text":"FaithTheDreamside","indices":[45,63]},{"text":"ValiantComics","indices":[80,94]}],"urls":[],"user_mentions":[{"screen_name":"S_Marguerite","name":"Marguerite Sauvage","id":112990433,"id_str":"112990433","indices":[3,16]},{"screen_name":"Jody_Houser","name":"The Haunting of Jody Houser \u2712\ufe0f\ud83d\uddef\ufe0f\ud83c\udfb2","id":15566406,"id_str":"15566406","indices":[112,124]}],"symbols":[]},"favorited":false,"retweeted":false,"filter_level":"low","lang":"en","timestamp_ms":"1540259753044"}
{"created_at":"Tue Oct 23 01:55:53 +0000 2018","id":1054551953936650241,"id_str":"1054551953936650241","text":"@gewozahiweg Hello, my name is Sergei, I am a founder of private trading community \u00ab10x club\u00bb. Now we opened our do\u2026 https:\/\/t.co\/lwYYPOfvYX","display_text_range":[13,140],"source":"\u003ca href=\"http:\/\/twitter.com\/download\/android\" rel=\"nofollow\"\u003eTwitter for Android\u003c\/a\u003e","truncated":true,"in_reply_to_status_id":1054551765113221120,"in_reply_to_status_id_str":"1054551765113221120","in_reply_to_user_id":2453856685,"in_reply_to_user_id_str":"2453856685","in_reply_to_screen_name":"gewozahiweg","user":{"id":1053788840341786625,"id_str":"1053788840341786625","name":"Toni","screen_name":"Toni19622291","location":null,"url":null,"description":"Receive daily signals and portfolio tips from a veteran crypto trader and become part of a strong Telegram crypto trading group. https:\/\/t.me\/symetraplatform","translator_type":"none","protected":false,"verified":false,"followers_count":0,"friends_count":0,"listed_count":0,"favourites_count":0,"statuses_count":45,"created_at":"Sat Oct 20 23:23:32 +0000 2018","utc_offset":null,"time_zone":null,"geo_enabled":false,"lang":"en","contributors_enabled":false,"is_translator":false,"profile_background_color":"F5F8FA","profile_background_image_url":"","profile_background_image_url_https":"","profile_background_tile":false,"profile_link_color":"1DA1F2","profile_sidebar_border_color":"C0DEED","profile_sidebar_fill_color":"DDEEF6","profile_text_color":"333333","profile_use_background_image":true,"profile_image_url":"http:\/\/abs.twimg.com\/sticky\/default_profile_images\/default_profile_normal.png","profile_image_url_https":"https:\/\/abs.twimg.com\/sticky\/default_profile_images\/default_profile_normal.png","profile_banner_url":"https:\/\/pbs.twimg.com\/profile_banners\/1053788840341786625\/1540228560","default_profile":true,"default_profile_image":false,"following":null,"follow_request_sent":null,"notifications":null},"geo":null,"coordinates":null,"place":null,"contributors":null,"is_quote_status":false,"extended_tweet":{"full_text":"@gewozahiweg Hello, my name is Sergei, I am a founder of private trading community \u00ab10x club\u00bb. Now we opened our doors for 100 people, join and get High Quality signals for new exchanges \u27a1 https:\/\/t.co\/2M7SxBPnYv\n\n$STORJ #Ethereum \n\n\u2b55 2045421763","display_text_range":[13,245],"entities":{"hashtags":[{"text":"Ethereum","indices":[221,230]}],"urls":[{"url":"https:\/\/t.co\/2M7SxBPnYv","expanded_url":"https:\/\/t.me\/symetraplatform","display_url":"t.me\/symetraplatform","indices":[189,212]}],"user_mentions":[{"screen_name":"gewozahiweg","name":"Ulysses Boerderman","id":2453856685,"id_str":"2453856685","indices":[0,12]}],"symbols":[{"text":"STORJ","indices":[214,220]}]}},"quote_count":0,"reply_count":0,"retweet_count":0,"favorite_count":0,"entities":{"hashtags":[],"urls":[{"url":"https:\/\/t.co\/lwYYPOfvYX","expanded_url":"https:\/\/twitter.com\/i\/web\/status\/1054551953936650241","display_url":"twitter.com\/i\/web\/status\/1\u2026","indices":[117,140]}],"user_mentions":[{"screen_name":"gewozahiweg","name":"Ulysses Boerderman","id":2453856685,"id_str":"2453856685","indices":[0,12]}],"symbols":[]},"favorited":false,"retweeted":false,"possibly_sensitive":false,"filter_level":"low","lang":"en","timestamp_ms":"1540259753103"}
